<Alloy>
        <Model src="todo"/>
        <Window title="New ToDo Window" layout="vertical">
                <View>
                        <Label>Titolo</Label>
                        <TextField id="titoloTxt" value="{todo.title}" returnKeyType="Ti.UI.RETURNKEY_NEXT" onReturn="focusLocation"/>
                </View>
                <View onClick="blurKeyboard">
                        <Label>Location</Label>
                        <TextField id="locationTxt" value="{todo.location}" onReturn="blurKeyboard" />
                        <Button id="mapButton" onClick="geolocateToDo"/>
                </View>
                <View onClick="blurKeyboard">
                        <Label>Allarme</Label>
                        <Switch id="alarmSw" value="false"  value="{todo.alarm}" onChange="blurKeyboard" />
                </View>
                <View>
                        <Label>Scadenza</Label>
                        <Button id="dateBtn" title="{todo.duedate}" onClick="openDueDateWindow"/>
                </View>
                <View height="Ti.UI.FILL">
                        <ImageView id="iv" image="{todo.image}" onClick="chooseImg"/>
                        <Button id="saveToDo" onClick="saveToDo">Salva ToDo</Button>
                </View>

        </Window>
</Alloy>